lib2dlp/CreatekuduSQL.py
lib2dlp/FileScan.py
lib2dlp/InsertMysql.py
lib2dlp/MultiUpload.py
lib2dlp/PopupMenu.py
lib2dlp/PySTAF.py
lib2dlp/PySTAFLog.py
lib2dlp/PySTAFMon.py
lib2dlp/PythonServiceOCR.py
lib2dlp/SSH.py
lib2dlp/WinAction.py
lib2dlp/Windows.py
lib2dlp/__init__.py
lib2dlp/bbb.py
lib2dlp/check.py
lib2dlp/code.py
lib2dlp/edlp.py
lib2dlp/exchange.py
lib2dlp/https.py
lib2dlp/menu.py
lib2dlp/mouse.py
lib2dlp/multilang.py
lib2dlp/office.py
lib2dlp/outlook.py
lib2dlp/pyauto.py
lib2dlp/pywin.py
lib2dlp/refuse.py
lib2dlp/smtp.py
lib2dlp/t.py
lib2dlp/telnet.py
lib2dlp/testocr.py
lib2dlp/web.py
lib2dlp/wechat.py
lib2dlp/AutoTest/__init__.py
lib2dlp/AutoTest/config.json
lib2dlp/AutoTest/configAllAuth.json
lib2dlp/AutoTest/configAllAuthAdmin.json
lib2dlp/AutoTest/configAllDisAuth.json
lib2dlp/AutoTest/configAllDisAuthAdmin.json
lib2dlp/AutoTest/configDisCopy.json
lib2dlp/AutoTest/configDisCopyAdmin.json
lib2dlp/AutoTest/configDisOfflineUse.json
lib2dlp/AutoTest/configDisOfflineUseAdmin.json
lib2dlp/AutoTest/configDisPrint.json
lib2dlp/AutoTest/configDisPrintAdmin.json
lib2dlp/AutoTest/configDisPrintScn.json
lib2dlp/AutoTest/configDisPrintScnAdmin.json
lib2dlp/AutoTest/configDisReAuth.json
lib2dlp/AutoTest/configDisReAuthAdmin.json
lib2dlp/Endpoint-Performance/__init__.py
lib2dlp/Endpoint-Performance/bootup.py
lib2dlp/Endpoint-Performance/time.py
lib2dlp/Endpoint-Performance/performance/-test.py
lib2dlp/Endpoint-Performance/performance/DlpScanDiscove.py
lib2dlp/Endpoint-Performance/performance/IEOpen.py
lib2dlp/Endpoint-Performance/performance/Printer.au3
lib2dlp/Endpoint-Performance/performance/UsbDriver.au3
lib2dlp/Endpoint-Performance/performance/__init__.py
lib2dlp/Endpoint-Performance/performance/autogui.py
lib2dlp/Endpoint-Performance/performance/autoinput.py
lib2dlp/Endpoint-Performance/performance/autoutil.py
lib2dlp/Endpoint-Performance/performance/bbb.py
lib2dlp-0.0.10.dist-info/METADATA
lib2dlp-0.0.10.dist-info/RECORD
lib2dlp-0.0.10.dist-info/WHEEL
lib2dlp-0.0.10.dist-info/top_level.txt
