Metadata-Version: 2.1
Name: lib2dlp
Version: 0.0.10
Summary: Data Loss Prevention (DLP) TEST
Home-page: https://pypi.org/project/lib2dlp/#files
Author: luoxianghui
Author-email: lxh_xwj@126.com
License: Apache 2.0
Keywords: pip,dlp,dlplib,libdlp
Platform: Linux; Windows
Classifier: Development Status :: 3 - Alpha
Classifier: Intended Audience :: Developers
Classifier: License :: OSI Approved :: Apache Software License
Classifier: Programming Language :: Python
Classifier: Programming Language :: Python :: 2.7
Classifier: Operating System :: OS Independent
Classifier: Topic :: Internet
Requires-Python: >=2.7.14
Requires-Dist: requests
Requires-Dist: selenium
Requires-Dist: paramiko
Requires-Dist: xlrd
Requires-Dist: xlwt
Requires-Dist: python-docx
Requires-Dist: python-pptx
Requires-Dist: pygame
Requires-Dist: canvas
Requires-Dist: reportlab
Requires-Dist: wmi
Requires-Dist: psutil
Requires-Dist: comtypes
Requires-Dist: configobj
Requires-Dist: configparser
Requires-Dist: faker
Requires-Dist: pyinstaller
Requires-Dist: docx
Requires-Dist: apscheduler (==2.1.2)
Requires-Dist: pycrypto
